README.md
setup.py
tests/__init__.py
tests/conftest.py
tests/test_event_publisher.py
tests/test_sns.py
tests/test_sqs.py
zeel_publisher/__init__.py
zeel_publisher/config.py
zeel_publisher/event_publisher.py
zeel_publisher/sns.py
zeel_publisher/sqs.py
zeel_publisher.egg-info/PKG-INFO
zeel_publisher.egg-info/SOURCES.txt
zeel_publisher.egg-info/dependency_links.txt
zeel_publisher.egg-info/requires.txt
zeel_publisher.egg-info/top_level.txt