Metadata-Version: 2.1
Name: zeel-publisher
Version: 1.1.3
Summary: A package for publishing to SNS
Home-page: https://github.com/zeel-dev/zeel-publisher
Author: Zeel
Author-email: engineering@zeel.com
License: UNKNOWN
Platform: UNKNOWN
Classifier: Programming Language :: Python :: 3
Classifier: License :: OSI Approved :: MIT License
Classifier: Operating System :: OS Independent
Requires-Python: ==3.6.1
